jumpstarter_protocol/__init__.py
jumpstarter_protocol/py.typed
jumpstarter_protocol/jumpstarter/__init__.py
jumpstarter_protocol/jumpstarter/client/__init__.py
jumpstarter_protocol/jumpstarter/client/v1/__init__.py
jumpstarter_protocol/jumpstarter/client/v1/client_pb2.py
jumpstarter_protocol/jumpstarter/client/v1/client_pb2_grpc.py
jumpstarter_protocol/jumpstarter/v1/__init__.py
jumpstarter_protocol/jumpstarter/v1/common_pb2.py
jumpstarter_protocol/jumpstarter/v1/common_pb2_grpc.py
jumpstarter_protocol/jumpstarter/v1/jumpstarter_pb2.py
jumpstarter_protocol/jumpstarter/v1/jumpstarter_pb2_grpc.py
jumpstarter_protocol/jumpstarter/v1/kubernetes_pb2.py
jumpstarter_protocol/jumpstarter/v1/kubernetes_pb2_grpc.py
jumpstarter_protocol/jumpstarter/v1/router_pb2.py
jumpstarter_protocol/jumpstarter/v1/router_pb2_grpc.py
jumpstarter_protocol-0.7.4.dist-info/METADATA
jumpstarter_protocol-0.7.4.dist-info/WHEEL
jumpstarter_protocol-0.7.4.dist-info/RECORD
