Metadata-Version: 2.4
Name: jumpstarter-protocol
Version: 0.7.4
Project-URL: Homepage, https://jumpstarter.dev
Project-URL: source_archive, https://github.com/jumpstarter-dev/repo/archive/c5d38de69eadbb8eb0388bcfe3430a679fff0059.zip
Author-email: Kirk Brauer <kbrauer@hatci.com>
License-Expression: Apache-2.0
Requires-Python: >=3.11
Requires-Dist: googleapis-common-protos>=1.69.1
Requires-Dist: grpcio>=1.66.1
Requires-Dist: protobuf>=6.30.1
